Pexels/__init__.py
Pexels/client.py
Pexels/constants.py
Pexels/errors.py
Pexels/types.py
python_pexels-1.0.dev1.dist-info/LICENSE
python_pexels-1.0.dev1.dist-info/METADATA
python_pexels-1.0.dev1.dist-info/WHEEL
python_pexels-1.0.dev1.dist-info/top_level.txt
python_pexels-1.0.dev1.dist-info/RECORD
